pyubxutils/__init__.py
pyubxutils/_version.py
pyubxutils/exceptions.py
pyubxutils/globals.py
pyubxutils/helpers.py
pyubxutils/ubxbase.py
pyubxutils/ubxcompare.py
pyubxutils/ubxload.py
pyubxutils/ubxsave.py
pyubxutils/ubxsetrate.py
pyubxutils/ubxsimulator.py
pyubxutils/ubxsimulator_cli.py
pyubxutils-1.0.5.dist-info/licenses/LICENSE
pyubxutils-1.0.5.dist-info/METADATA
pyubxutils-1.0.5.dist-info/WHEEL
pyubxutils-1.0.5.dist-info/entry_points.txt
pyubxutils-1.0.5.dist-info/top_level.txt
pyubxutils-1.0.5.dist-info/RECORD
