Metadata-Version: 2.4
Name: pyubxutils
Version: 1.0.5
Summary: UBX Protocol Command Line Utilities
Author-email: Steve Smith <semuadmin@semuconsulting.com>
Maintainer-email: Steve Smith <semuadmin@semuconsulting.com>
License-Expression: BSD-3-Clause
Project-URL: homepage, https://github.com/semuconsulting/pyubx2
Project-URL: documentation, https://www.semuconsulting.com/pyubx2/
Project-URL: repository, https://github.com/semuconsulting/pyubx2
Project-URL: changelog, https://github.com/semuconsulting/pyubx2/blob/master/RELEASE_NOTES.md
Classifier: Operating System :: OS Independent
Classifier: Development Status :: 5 - Production/Stable
Classifier: Environment :: MacOS X
Classifier: Environment :: Win32 (MS Windows)
Classifier: Environment :: X11 Applications
Classifier: Environment :: Console
Classifier: Intended Audience :: Developers
Classifier: Intended Audience :: Science/Research
Classifier: Intended Audience :: End Users/Desktop
Classifier: Programming Language :: Python :: 3
Classifier: Programming Language :: Python :: 3.10
Classifier: Programming Language :: Python :: 3.11
Classifier: Programming Language :: Python :: 3.12
Classifier: Programming Language :: Python :: 3.13
Classifier: Programming Language :: Python :: 3.14
Classifier: Topic :: Utilities
Classifier: Topic :: Software Development :: Libraries :: Python Modules
Classifier: Topic :: Scientific/Engineering :: GIS
Requires-Python: >=3.10
License-File: LICENSE
Requires-Dist: pyserial>=3.5
Requires-Dist: pyubx2>=1.2.58
Dynamic: license-file
